accel/tpu/rtl/sram.sv
/*
SRAM controller for CMOD A7 (ISSI IS61/64WV5128, 512K x 8 async SRAM)
SRAM datasheet: https://www.issi.com/WW/pdf/61-64WV5128Axx-Bxx.pdf

Single-word read/write engine with a simple start/busy/done handshake.
The request (addr/din/we) is latched on `start`, so the caller only has to
hold the inputs valid for the cycle `start` is asserted.

FSM: IDLE -> (WRITE|READ) -> WAIT -> IDLE
  WAIT holds for CLOCKS_PER_ACCESS cycles so the asynchronous access time is
  met before we sample read data / end the write pulse.
*/

module sram_controller #(
    parameter integer CLOCKS_PER_ACCESS = 2,
    parameter integer ADDR_W = 19,
    parameter integer DATA_W = 8
) (
    input  logic clk,
    input  logic rst_n,

    // user signals
    input  logic start,
    input  logic we,
    input  logic [ADDR_W-1:0] addr,
    input  logic [DATA_W-1:0] din,
    output logic [DATA_W-1:0] dout,
    output logic busy,
    output logic done,

    // chip signals
    output logic [ADDR_W-1:0] sram_addr,
    inout  wire  [DATA_W-1:0] sram_data,   // inout must be a net, not a var
    output logic sram_we,
    output logic sram_ce,
    output logic sram_oen
);
    localparam [1:0] IDLE = 2'b00, WRITE = 2'b01, READ = 2'b10, WAIT = 2'b11;

    reg [1:0] state, state_n;
    reg [7:0] counter;

    // latched request so the caller need only hold inputs during `start`
    reg [ADDR_W-1:0] addr_q;
    reg [DATA_W-1:0] din_q;
    reg              wr_q;      // 1 = latched op is a write
    reg              drive_en;  // 1 = FPGA drives the bidirectional bus

    // Only drive the bus while we own it (a write); otherwise release to Hi-Z
    // so the SRAM can drive it during reads.
    assign sram_data = drive_en ? din_q : {DATA_W{1'bz}};
    assign sram_addr = addr_q;

    // next-state logic (default: hold current state)
    always_comb begin
        state_n = state;
        case (state)
            IDLE:  if (start) state_n = we ? WRITE : READ;
            WRITE: state_n = WAIT;
            READ:  state_n = WAIT;
            WAIT:  if (counter >= CLOCKS_PER_ACCESS) state_n = IDLE;
        endcase
    end

    always_ff @(posedge clk or negedge rst_n) begin
        if (!rst_n) begin
            state    <= IDLE;
            counter  <= 8'b0;
            sram_we  <= 1'b1;
            sram_ce  <= 1'b1;
            sram_oen <= 1'b1;
            drive_en <= 1'b0;
            busy     <= 1'b0;
            done     <= 1'b0;
            dout     <= '0;
            addr_q   <= '0;
            din_q    <= '0;
            wr_q     <= 1'b0;
        end else begin
            state <= state_n;
            done  <= 1'b0;  // one-cycle strobe, default low

            case (state)
                IDLE: begin
                    counter  <= 8'b0;
                    sram_ce  <= 1'b1;   // deselect while idle
                    sram_we  <= 1'b1;
                    sram_oen <= 1'b1;
                    drive_en <= 1'b0;
                    busy     <= start;  // accept the request this cycle
                    if (start) begin
                        addr_q <= addr;
                        din_q  <= din;
                        wr_q   <= we;
                    end
                end
                WRITE: begin
                    busy     <= 1'b1;
                    sram_ce  <= 1'b0;
                    sram_we  <= 1'b0;   // assert write pulse
                    sram_oen <= 1'b1;   // SRAM outputs off during a write
                    drive_en <= 1'b1;   // drive din onto the bus
                end
                READ: begin
                    busy     <= 1'b1;
                    sram_ce  <= 1'b0;
                    sram_we  <= 1'b1;
                    sram_oen <= 1'b0;   // let the SRAM drive the bus
                    drive_en <= 1'b0;
                end
                WAIT: begin
                    busy    <= 1'b1;
                    counter <= counter + 1'b1;
                    if (wr_q) begin
                        // End the write pulse while addr/data are still held,
                        // so the word is committed on the WE# rising edge.
                        sram_we <= 1'b1;
                    end else begin
                        // OE# has been low long enough; capture read data.
                        dout <= sram_data;
                    end
                    if (state_n == IDLE) begin
                        done     <= 1'b1;
                        busy     <= 1'b0;
                        sram_ce  <= 1'b1;
                        sram_oen <= 1'b1;
                        drive_en <= 1'b0;
                    end
                end
            endcase
        end
    end
endmodule

accel/tpu/tb/sram_tb.sv
// -----------------------------------------------------------------------------
// sram_tb.sv — self-checking testbench for accel/tpu/rtl/sram.sv
//
// Drives the sram_controller through its start/busy/done handshake and connects
// its chip-side bus to a behavioral model of the CMOD A7 Cellular RAM
// (ISSI IS61/64WV5128, 512K x 8 asynchronous SRAM):
//
//   * output driven only when CE#=0, OE#=0, WE#=1 (a read); Hi-Z otherwise
//   * a word is committed on the WE# rising edge while CE# is low
//   * a small access delay models the asynchronous read path (tAA)
//
// Checks: write/read round-trips over data patterns and address corners, that
// `done` is a single-cycle pulse, `busy` frames the whole op, and that the bus
// is released (Hi-Z) whenever the controller is idle so there's no contention.
//
// Run:  make TEST=sram sim         (iverilog -g2012 + vvp)
// -----------------------------------------------------------------------------

`timescale 1ns/1ps

module sram_tb;

    // ---- Parameters (must match the DUT instance) ---------------------------
    localparam int CLOCKS_PER_ACCESS = 2;
    localparam int ADDR_W            = 19;
    localparam int DATA_W            = 8;

    // -------------------------------------------------------------------------
    // Clock / reset.
    // -------------------------------------------------------------------------
    logic clk = 1'b0;
    logic rst_n = 1'b0;
    always #5 clk = ~clk;   // 100 MHz

    // -------------------------------------------------------------------------
    // DUT interface.
    // -------------------------------------------------------------------------
    logic                start;
    logic                we;
    logic [ADDR_W-1:0]   addr;
    logic [DATA_W-1:0]   din;
    logic [DATA_W-1:0]   dout;
    logic                busy;
    logic                done;

    wire  [ADDR_W-1:0]   sram_addr;
    wire  [DATA_W-1:0]   sram_data;
    wire                 sram_we;
    wire                 sram_ce;
    wire                 sram_oen;

    sram_controller #(
        .CLOCKS_PER_ACCESS(CLOCKS_PER_ACCESS),
        .ADDR_W(ADDR_W), .DATA_W(DATA_W)
    ) dut (
        .clk(clk), .rst_n(rst_n),
        .start(start), .we(we), .addr(addr), .din(din),
        .dout(dout), .busy(busy), .done(done),
        .sram_addr(sram_addr), .sram_data(sram_data),
        .sram_we(sram_we), .sram_ce(sram_ce), .sram_oen(sram_oen)
    );

    // -------------------------------------------------------------------------
    // Behavioral async SRAM model.
    // -------------------------------------------------------------------------
    localparam int MEM_SZ = 1 << ADDR_W;
    logic [DATA_W-1:0] mem [0:MEM_SZ-1];

    // Read: drive the bus (after a modest access delay) only when selected,
    // output-enabled, and not writing. Released to Hi-Z otherwise. The #3 on the
    // continuous assign models the asynchronous access time (tAA).
    wire mem_drives = (sram_ce == 1'b0) && (sram_oen == 1'b0) && (sram_we == 1'b1);
    assign #3 sram_data = mem_drives ? mem[sram_addr] : {DATA_W{1'bz}};

    // Write: commit the word on the WE# rising edge while the chip is selected.
    always @(posedge sram_we) begin
        if (sram_ce == 1'b0) mem[sram_addr] <= sram_data;
    end

    // -------------------------------------------------------------------------
    // Bookkeeping.
    // -------------------------------------------------------------------------
    int errors = 0;
    int checks = 0;

    task automatic check(input logic cond, input string tag);
        checks++;
        if (!cond) begin
            errors++;
            $display("  FAIL %s (t=%0t)", tag, $time);
        end
    endtask

    // -------------------------------------------------------------------------
    // Handshake drivers. Inputs change on negedge; the DUT samples on posedge.
    // Each op asserts start for exactly one cycle, then waits for `done`,
    // asserting along the way that busy frames the transaction and done is a
    // single-cycle pulse.
    // -------------------------------------------------------------------------
    task automatic do_write(input [ADDR_W-1:0] a, input [DATA_W-1:0] d);
        int done_cycles;
        @(negedge clk);
        addr = a; din = d; we = 1'b1; start = 1'b1;
        @(negedge clk);
        start = 1'b0;
        check(busy, "write: busy asserted after start");
        done_cycles = 0;
        while (!done) begin
            check(busy, "write: busy stays high until done");
            @(negedge clk);
        end
        // done is high now; confirm it drops next cycle (single-cycle pulse).
        @(negedge clk);
        check(!done, "write: done is a single-cycle pulse");
    endtask

    task automatic do_read(input [ADDR_W-1:0] a, output [DATA_W-1:0] d);
        @(negedge clk);
        addr = a; we = 1'b0; start = 1'b1;
        @(negedge clk);
        start = 1'b0;
        check(busy, "read: busy asserted after start");
        while (!done) begin
            check(busy, "read: busy stays high until done");
            @(negedge clk);
        end
        d = dout;
        @(negedge clk);
        check(!done, "read: done is a single-cycle pulse");
    endtask

    task automatic write_read_check(input [ADDR_W-1:0] a, input [DATA_W-1:0] d,
                                     input string tag);
        logic [DATA_W-1:0] rd;
        do_write(a, d);
        // Bus must be released once the controller is idle again.
        check(sram_data === {DATA_W{1'bz}}, {tag, ": bus Hi-Z when idle"});
        do_read(a, rd);
        check(rd === d, tag);
        if (rd !== d)
            $display("    @0x%05h: wrote 0x%02h, read 0x%02h", a, d, rd);
    endtask

    // -------------------------------------------------------------------------
    // Stimulus.
    // -------------------------------------------------------------------------
    logic [DATA_W-1:0] rd;
    initial begin
        $dumpfile("sram_tb.vcd");
        $dumpvars(0, sram_tb);

        start = 1'b0; we = 1'b0; addr = '0; din = '0;

        // Reset.
        repeat (4) @(posedge clk);
        rst_n = 1'b1;
        @(posedge clk);

        // Bus should be idle/Hi-Z coming out of reset.
        check(sram_data === {DATA_W{1'bz}}, "post-reset: bus Hi-Z");
        check(!busy && !done, "post-reset: idle");

        $display("==== SRAM controller testbench ====");

        // Data patterns at a fixed address.
        write_read_check(19'h00010, 8'h00, "pattern 0x00");
        write_read_check(19'h00010, 8'hFF, "pattern 0xFF");
        write_read_check(19'h00010, 8'hA5, "pattern 0xA5");
        write_read_check(19'h00010, 8'h5A, "pattern 0x5A");

        // Address corners.
        write_read_check(19'h00000,       8'h11, "addr min");
        write_read_check({ADDR_W{1'b1}},  8'h22, "addr max");
        write_read_check(19'h40000,       8'h33, "addr bit18");
        write_read_check(19'h2AAAA,       8'h44, "addr walk-1");
        write_read_check(19'h15555,       8'h55, "addr walk-0");

        // Distinct values across a block, then read all back — checks that each
        // write commits to its own address (no address/data aliasing).
        for (int i = 0; i < 32; i++)
            do_write(19'h00100 + i[ADDR_W-1:0], (i * 7 + 3));
        for (int i = 0; i < 32; i++) begin
            do_read(19'h00100 + i[ADDR_W-1:0], rd);
            check(rd === 8'((i * 7 + 3)), $sformatf("block[%0d]", i));
            if (rd !== 8'((i * 7 + 3)))
                $display("    block[%0d]: exp 0x%02h got 0x%02h", i, 8'((i*7+3)), rd);
        end

        // Overwrite an existing address to confirm old data is replaced.
        do_write(19'h00100, 8'hDE);
        do_read (19'h00100, rd);
        check(rd === 8'hDE, "overwrite");

        // Summary.
        $display("==== done: %0d checks, %0d errors ====", checks, errors);
        if (errors == 0) $display("SRAM: ALL TESTS PASSED");
        else             $display("SRAM: FAILED (%0d errors)", errors);
        $finish;
    end

    // Watchdog.
    initial begin
        #100000;
        $display("SRAM: TIMEOUT — DUT did not complete");
        $fatal(1);
    end

endmodule

accel/tpu/tb/sram_tb.vcd
$date
	Sun Aug 16 23:56:52 2026
$end
$version
	Icarus Verilog
$end
$timescale
	1ps
$end
$scope module sram_tb $end
$var wire 1 ! mem_drives $end
$var wire 8 " sram_data [7:0] $end
$var wire 1 # sram_we $end
$var wire 1 $ sram_oen $end
$var wire 1 % sram_ce $end
$var wire 19 & sram_addr [18:0] $end
$var wire 8 ' dout [7:0] $end
$var wire 1 ( done $end
$var wire 1 ) busy $end
$var parameter 32 * ADDR_W $end
$var parameter 32 + CLOCKS_PER_ACCESS $end
$var parameter 32 , DATA_W $end
$var parameter 32 - MEM_SZ $end
$var reg 19 . addr [18:0] $end
$var reg 1 / clk $end
$var reg 8 0 din [7:0] $end
$var reg 8 1 rd [7:0] $end
$var reg 1 2 rst_n $end
$var reg 1 3 start $end
$var reg 1 4 we $end
$var integer 32 5 checks [31:0] $end
$var integer 32 6 errors [31:0] $end
$scope module dut $end
$var wire 19 7 addr [18:0] $end
$var wire 1 / clk $end
$var wire 8 8 din [7:0] $end
$var wire 1 2 rst_n $end
$var wire 19 9 sram_addr [18:0] $end
$var wire 8 : sram_data [7:0] $end
$var wire 1 3 start $end
$var wire 1 4 we $end
$var parameter 32 ; ADDR_W $end
$var parameter 32 < CLOCKS_PER_ACCESS $end
$var parameter 32 = DATA_W $end
$var parameter 2 > IDLE $end
$var parameter 2 ? READ $end
$var parameter 2 @ WAIT $end
$var parameter 2 A WRITE $end
$var reg 19 B addr_q [18:0] $end
$var reg 1 ) busy $end
$var reg 8 C counter [7:0] $end
$var reg 8 D din_q [7:0] $end
$var reg 1 ( done $end
$var reg 8 E dout [7:0] $end
$var reg 1 F drive_en $end
$var reg 1 % sram_ce $end
$var reg 1 $ sram_oen $end
$var reg 1 # sram_we $end
$var reg 2 G state [1:0] $end
$var reg 2 H state_n [1:0] $end
$var reg 1 I wr_q $end
$upscope $end
$scope begin $ivl_for_loop0 $end
$var integer 32 J i [31:0] $end
$upscope $end
$scope begin $ivl_for_loop1 $end
$var integer 32 K i [31:0] $end
$upscope $end
$scope task check $end
$upscope $end
$scope task do_read $end
$upscope $end
$scope task do_write $end
$upscope $end
$scope task write_read_check $end
$upscope $end
$upscope $end
$enddefinitions $end
$comment Show the parameter values. $end
$dumpall
b1 A
b11 @
b10 ?
b0 >
b1000 =
b10 <
b10011 ;
b10000000000000000000 -
b1000 ,
b10 +
b10011 *
$end
#0
$dumpvars
b0 K
b0 J
xI
bx H
bx G
xF
bx E
bx D
bx C
bx B
bx :
bx 9
b0 8
b0 7
b0 6
b0 5
04
03
02
bx 1
b0 0
0/
b0 .
x)
x(
bx '
bx &
x%
x$
x#
bx "
x!
$end
#5000
0!
b0 H
0I
b0 D
b0 &
b0 9
b0 B
b0 '
b0 E
0(
0)
0F
1$
1%
1#
b0 C
b0 G
1/
#8000
bz "
bz :
#10000
0/
#15000
1/
#20000
0/
#25000
1/
#30000
0/
#35000
12
1/
#40000
0/
#45000
b10 5
1/
#50000
b1 H
13
14
b10000 .
b10000 7
0/
#55000
b11 H
1I
b10000 &
b10000 9
b10000 B
1)
b1 G
1/
#60000
b11 H
b100 5
03
0/
#65000
b0 "
b0 :
1F
0#
0%
b11 G
1/
#70000
b101 5
0/
#75000
1#
b1 C
1/
#80000
b110 5
0/
#85000
b0 H
b10 C
1/
#90000
b111 5
0/
#95000
bz "
bz :
0F
1%
0)
1(
b11 C
b0 G
1/
#100000
0/
#105000
b0 C
0(
1/
#110000
b1001 5
0/
#115000
1/
#120000
b10 H
13
04
0/
#125000
b11 H
0I
1)
b10 G
1/
#130000
b11 H
b1011 5
03
0/
#135000
1!
0$
0%
b11 G
1/
#138000
b0 "
b0 :
#140000
b1100 5
0/
#145000
b1 C
1/
#150000
b1101 5
0/
#155000
b0 H
b10 C
1/
#160000
b1110 5
0/
#165000
0!
1$
1%
0)
1(
b11 C
b0 G
1/
#168000
bz "
bz :
#170000
0/
#175000
b0 C
0(
1/
#180000
b10000 5
0/
#185000
1/
#190000
b1 H
13
14
b11111111 0
b11111111 8
0/
#195000
b11 H
1I
b11111111 D
1)
b1 G
1/
#200000
b11 H
b10010 5
03
0/
#205000
b11111111 "
b11111111 :
1F
0#
0%
b11 G
1/
#210000
b10011 5
0/
#215000
1#
b1 C
1/
#220000
b10100 5
0/
#225000
b0 H
b10 C
1/
#230000
b10101 5
0/
#235000
bz "
bz :
0F
1%
0)
1(
b11 C
b0 G
1/
#240000
0/
#245000
b0 C
0(
1/
#250000
b10111 5
0/
#255000
1/
#260000
b10 H
13
04
0/
#265000
b11 H
0I
1)
b10 G
1/
#270000
b11 H
b11001 5
03
0/
#275000
1!
0$
0%
b11 G
1/
#278000
b11111111 "
b11111111 :
#280000
b11010 5
0/
#285000
b11111111 '
b11111111 E
b1 C
1/
#290000
b11011 5
0/
#295000
b0 H
b10 C
1/
#300000
b11100 5
0/
#305000
0!
1$
1%
0)
1(
b11 C
b0 G
1/
#308000
bz "
bz :
#310000
0/
#315000
b0 C
0(
1/
#320000
b11110 5
0/
#325000
1/
#330000
b1 H
13
14
b10100101 0
b10100101 8
0/
#335000
b11 H
1I
b10100101 D
1)
b1 G
1/
#340000
b11 H
b100000 5
03
0/
#345000
b10100101 "
b10100101 :
1F
0#
0%
b11 G
1/
#350000
b100001 5
0/
#355000
1#
b1 C
1/
#360000
b100010 5
0/
#365000
b0 H
b10 C
1/
#370000
b100011 5
0/
#375000
bz "
bz :
0F
1%
0)
1(
b11 C
b0 G
1/
#380000
0/
#385000
b0 C
0(
1/
#390000
b100101 5
0/
#395000
1/
#400000
b10 H
13
04
0/
#405000
b11 H
0I
1)
b10 G
1/
#410000
b11 H
b100111 5
03
0/
#415000
1!
0$
0%
b11 G
1/
#418000
b10100101 "
b10100101 :
#420000
b101000 5
0/
#425000
b10100101 '
b10100101 E
b1 C
1/
#430000
b101001 5
0/
#435000
b0 H
b10 C
1/
#440000
b101010 5
0/
#445000
0!
1$
1%
0)
1(
b11 C
b0 G
1/
#448000
bz "
bz :
#450000
0/
#455000
b0 C
0(
1/
#460000
b101100 5
0/
#465000
1/
#470000
b1 H
13
14
b1011010 0
b1011010 8
0/
#475000
b11 H
1I
b1011010 D
1)
b1 G
1/
#480000
b11 H
b101110 5
03
0/
#485000
b1011010 "
b1011010 :
1F
0#
0%
b11 G
1/
#490000
b101111 5
0/
#495000
1#
b1 C
1/
#500000
b110000 5
0/
#505000
b0 H
b10 C
1/
#510000
b110001 5
0/
#515000
bz "
bz :
0F
1%
0)
1(
b11 C
b0 G
1/
#520000
0/
#525000
b0 C
0(
1/
#530000
b110011 5
0/
#535000
1/
#540000
b10 H
13
04
0/
#545000
b11 H
0I
1)
b10 G
1/
#550000
b11 H
b110101 5
03
0/
#555000
1!
0$
0%
b11 G
1/
#558000
b1011010 "
b1011010 :
#560000
b110110 5
0/
#565000
b1011010 '
b1011010 E
b1 C
1/
#570000
b110111 5
0/
#575000
b0 H
b10 C
1/
#580000
b111000 5
0/
#585000
0!
1$
1%
0)
1(
b11 C
b0 G
1/
#588000
bz "
bz :
#590000
0/
#595000
b0 C
0(
1/
#600000
b111010 5
0/
#605000
1/
#610000
b1 H
13
14
b10001 0
b10001 8
b0 .
b0 7
0/
#615000
b11 H
1I
b10001 D
b0 &
b0 9
b0 B
1)
b1 G
1/
#620000
b11 H
b111100 5
03
0/
#625000
b10001 "
b10001 :
1F
0#
0%
b11 G
1/
#630000
b111101 5
0/
#635000
1#
b1 C
1/
#640000
b111110 5
0/
#645000
b0 H
b10 C
1/
#650000
b111111 5
0/
#655000
bz "
bz :
0F
1%
0)
1(
b11 C
b0 G
1/
#660000
0/
#665000
b0 C
0(
1/
#670000
b1000001 5
0/
#675000
1/
#680000
b10 H
13
04
0/
#685000
b11 H
0I
1)
b10 G
1/
#690000
b11 H
b1000011 5
03
0/
#695000
1!
0$
0%
b11 G
1/
#698000
b10001 "
b10001 :
#700000
b1000100 5
0/
#705000
b10001 '
b10001 E
b1 C
1/
#710000
b1000101 5
0/
#715000
b0 H
b10 C
1/
#720000
b1000110 5
0/
#725000
0!
1$
1%
0)
1(
b11 C
b0 G
1/
#728000
bz "
bz :
#730000
0/
#735000
b0 C
0(
1/
#740000
b1001000 5
0/
#745000
1/
#750000
b1 H
13
14
b100010 0
b100010 8
b1111111111111111111 .
b1111111111111111111 7
0/
#755000
b11 H
1I
b100010 D
b1111111111111111111 &
b1111111111111111111 9
b1111111111111111111 B
1)
b1 G
1/
#760000
b11 H
b1001010 5
03
0/
#765000
b100010 "
b100010 :
1F
0#
0%
b11 G
1/
#770000
b1001011 5
0/
#775000
1#
b1 C
1/
#780000
b1001100 5
0/
#785000
b0 H
b10 C
1/
#790000
b1001101 5
0/
#795000
bz "
bz :
0F
1%
0)
1(
b11 C
b0 G
1/
#800000
0/
#805000
b0 C
0(
1/
#810000
b1001111 5
0/
#815000
1/
#820000
b10 H
13
04
0/
#825000
b11 H
0I
1)
b10 G
1/
#830000
b11 H
b1010001 5
03
0/
#835000
1!
0$
0%
b11 G
1/
#838000
b100010 "
b100010 :
#840000
b1010010 5
0/
#845000
b100010 '
b100010 E
b1 C
1/
#850000
b1010011 5
0/
#855000
b0 H
b10 C
1/
#860000
b1010100 5
0/
#865000
0!
1$
1%
0)
1(
b11 C
b0 G
1/
#868000
bz "
bz :
#870000
0/
#875000
b0 C
0(
1/
#880000
b1010110 5
0/
#885000
1/
#890000
b1 H
13
14
b110011 0
b110011 8
b1000000000000000000 .
b1000000000000000000 7
0/
#895000
b11 H
1I
b110011 D
b1000000000000000000 &
b1000000000000000000 9
b1000000000000000000 B
1)
b1 G
1/
#900000
b11 H
b1011000 5
03
0/
#905000
b110011 "
b110011 :
1F
0#
0%
b11 G
1/
#910000
b1011001 5
0/
#915000
1#
b1 C
1/
#920000
b1011010 5
0/
#925000
b0 H
b10 C
1/
#930000
b1011011 5
0/
#935000
bz "
bz :
0F
1%
0)
1(
b11 C
b0 G
1/
#940000
0/
#945000
b0 C
0(
1/
#950000
b1011101 5
0/
#955000
1/
#960000
b10 H
13
04
0/
#965000
b11 H
0I
1)
b10 G
1/
#970000
b11 H
b1011111 5
03
0/
#975000
1!
0$
0%
b11 G
1/
#978000
b110011 "
b110011 :
#980000
b1100000 5
0/
#985000
b110011 '
b110011 E
b1 C
1/
#990000
b1100001 5
0/
#995000
b0 H
b10 C
1/
#1000000
b1100010 5
0/
#1005000
0!
1$
1%
0)
1(
b11 C
b0 G
1/
#1008000
bz "
bz :
#1010000
0/
#1015000
b0 C
0(
1/
#1020000
b1100100 5
0/
#1025000
1/
#1030000
b1 H
13
14
b1000100 0
b1000100 8
b101010101010101010 .
b101010101010101010 7
0/
#1035000
b11 H
1I
b1000100 D
b101010101010101010 &
b101010101010101010 9
b101010101010101010 B
1)
b1 G
1/
#1040000
b11 H
b1100110 5
03
0/
#1045000
b1000100 "
b1000100 :
1F
0#
0%
b11 G
1/
#1050000
b1100111 5
0/
#1055000
1#
b1 C
1/
#1060000
b1101000 5
0/
#1065000
b0 H
b10 C
1/
#1070000
b1101001 5
0/
#1075000
bz "
bz :
0F
1%
0)
1(
b11 C
b0 G
1/
#1080000
0/
#1085000
b0 C
0(
1/
#1090000
b1101011 5
0/
#1095000
1/
#1100000
b10 H
13
04
0/
#1105000
b11 H
0I
1)
b10 G
1/
#1110000
b11 H
b1101101 5
03
0/
#1115000
1!
0$
0%
b11 G
1/
#1118000
b1000100 "
b1000100 :
#1120000
b1101110 5
0/
#1125000
b1000100 '
b1000100 E
b1 C
1/
#1130000
b1101111 5
0/
#1135000
b0 H
b10 C
1/
#1140000
b1110000 5
0/
#1145000
0!
1$
1%
0)
1(
b11 C
b0 G
1/
#1148000
bz "
bz :
#1150000
0/
#1155000
b0 C
0(
1/
#1160000
b1110010 5
0/
#1165000
1/
#1170000
b1 H
13
14
b1010101 0
b1010101 8
b10101010101010101 .
b10101010101010101 7
0/
#1175000
b11 H
1I
b1010101 D
b10101010101010101 &
b10101010101010101 9
b10101010101010101 B
1)
b1 G
1/
#1180000
b11 H
b1110100 5
03
0/
#1185000
b1010101 "
b1010101 :
1F
0#
0%
b11 G
1/
#1190000
b1110101 5
0/
#1195000
1#
b1 C
1/
#1200000
b1110110 5
0/
#1205000
b0 H
b10 C
1/
#1210000
b1110111 5
0/
#1215000
bz "
bz :
0F
1%
0)
1(
b11 C
b0 G
1/
#1220000
0/
#1225000
b0 C
0(
1/
#1230000
b1111001 5
0/
#1235000
1/
#1240000
b10 H
13
04
0/
#1245000
b11 H
0I
1)
b10 G
1/
#1250000
b11 H
b1111011 5
03
0/
#1255000
1!
0$
0%
b11 G
1/
#1258000
b1010101 "
b1010101 :
#1260000
b1111100 5
0/
#1265000
b1010101 '
b1010101 E
b1 C
1/
#1270000
b1111101 5
0/
#1275000
b0 H
b10 C
1/
#1280000
b1111110 5
0/
#1285000
0!
1$
1%
0)
1(
b11 C
b0 G
1/
#1288000
bz "
bz :
#1290000
0/
#1295000
b0 C
0(
1/
#1300000
b10000000 5
0/
#1305000
1/
#1310000
b1 H
13
14
b11 0
b11 8
b100000000 .
b100000000 7
0/
#1315000
b11 H
1I
b11 D
b100000000 &
b100000000 9
b100000000 B
1)
b1 G
1/
#1320000
b11 H
b10000010 5
03
0/
#1325000
b11 "
b11 :
1F
0#
0%
b11 G
1/
#1330000
b10000011 5
0/
#1335000
1#
b1 C
1/
#1340000
b10000100 5
0/
#1345000
b0 H
b10 C
1/
#1350000
b10000101 5
0/
#1355000
bz "
bz :
0F
1%
0)
1(
b11 C
b0 G
1/
#1360000
0/
#1365000
b0 C
0(
1/
#1370000
b1 J
b10000110 5
0/
#1375000
1/
#1380000
b1 H
13
b1010 0
b1010 8
b100000001 .
b100000001 7
0/
#1385000
b11 H
b1010 D
b100000001 &
b100000001 9
b100000001 B
1)
b1 G
1/
#1390000
b11 H
b10001000 5
03
0/
#1395000
b1010 "
b1010 :
1F
0#
0%
b11 G
1/
#1400000
b10001001 5
0/
#1405000
1#
b1 C
1/
#1410000
b10001010 5
0/
#1415000
b0 H
b10 C
1/
#1420000
b10001011 5
0/
#1425000
bz "
bz :
0F
1%
0)
1(
b11 C
b0 G
1/
#1430000
0/
#1435000
b0 C
0(
1/
#1440000
b10 J
b10001100 5
0/
#1445000
1/
#1450000
b1 H
13
b10001 0
b10001 8
b100000010 .
b100000010 7
0/
#1455000
b11 H
b10001 D
b100000010 &
b100000010 9
b100000010 B
1)
b1 G
1/
#1460000
b11 H
b10001110 5
03
0/
#1465000
b10001 "
b10001 :
1F
0#
0%
b11 G
1/
#1470000
b10001111 5
0/
#1475000
1#
b1 C
1/
#1480000
b10010000 5
0/
#1485000
b0 H
b10 C
1/
#1490000
b10010001 5
0/
#1495000
bz "
bz :
0F
1%
0)
1(
b11 C
b0 G
1/
#1500000
0/
#1505000
b0 C
0(
1/
#1510000
b11 J
b10010010 5
0/
#1515000
1/
#1520000
b1 H
13
b11000 0
b11000 8
b100000011 .
b100000011 7
0/
#1525000
b11 H
b11000 D
b100000011 &
b100000011 9
b100000011 B
1)
b1 G
1/
#1530000
b11 H
b10010100 5
03
0/
#1535000
b11000 "
b11000 :
1F
0#
0%
b11 G
1/
#1540000
b10010101 5
0/
#1545000
1#
b1 C
1/
#1550000
b10010110 5
0/
#1555000
b0 H
b10 C
1/
#1560000
b10010111 5
0/
#1565000
bz "
bz :
0F
1%
0)
1(
b11 C
b0 G
1/
#1570000
0/
#1575000
b0 C
0(
1/
#1580000
b100 J
b10011000 5
0/
#1585000
1/
#1590000
b1 H
13
b11111 0
b11111 8
b100000100 .
b100000100 7
0/
#1595000
b11 H
b11111 D
b100000100 &
b100000100 9
b100000100 B
1)
b1 G
1/
#1600000
b11 H
b10011010 5
03
0/
#1605000
b11111 "
b11111 :
1F
0#
0%
b11 G
1/
#1610000
b10011011 5
0/
#1615000
1#
b1 C
1/
#1620000
b10011100 5
0/
#1625000
b0 H
b10 C
1/
#1630000
b10011101 5
0/
#1635000
bz "
bz :
0F
1%
0)
1(
b11 C
b0 G
1/
#1640000
0/
#1645000
b0 C
0(
1/
#1650000
b101 J
b10011110 5
0/
#1655000
1/
#1660000
b1 H
13
b100110 0
b100110 8
b100000101 .
b100000101 7
0/
#1665000
b11 H
b100110 D
b100000101 &
b100000101 9
b100000101 B
1)
b1 G
1/
#1670000
b11 H
b10100000 5
03
0/
#1675000
b100110 "
b100110 :
1F
0#
0%
b11 G
1/
#1680000
b10100001 5
0/
#1685000
1#
b1 C
1/
#1690000
b10100010 5
0/
#1695000
b0 H
b10 C
1/
#1700000
b10100011 5
0/
#1705000
bz "
bz :
0F
1%
0)
1(
b11 C
b0 G
1/
#1710000
0/
#1715000
b0 C
0(
1/
#1720000
b110 J
b10100100 5
0/
#1725000
1/
#1730000
b1 H
13
b101101 0
b101101 8
b100000110 .
b100000110 7
0/
#1735000
b11 H
b101101 D
b100000110 &
b100000110 9
b100000110 B
1)
b1 G
1/
#1740000
b11 H
b10100110 5
03
0/
#1745000
b101101 "
b101101 :
1F
0#
0%
b11 G
1/
#1750000
b10100111 5
0/
#1755000
1#
b1 C
1/
#1760000
b10101000 5
0/
#1765000
b0 H
b10 C
1/
#1770000
b10101001 5
0/
#1775000
bz "
bz :
0F
1%
0)
1(
b11 C
b0 G
1/
#1780000
0/
#1785000
b0 C
0(
1/
#1790000
b111 J
b10101010 5
0/
#1795000
1/
#1800000
b1 H
13
b110100 0
b110100 8
b100000111 .
b100000111 7
0/
#1805000
b11 H
b110100 D
b100000111 &
b100000111 9
b100000111 B
1)
b1 G
1/
#1810000
b11 H
b10101100 5
03
0/
#1815000
b110100 "
b110100 :
1F
0#
0%
b11 G
1/
#1820000
b10101101 5
0/
#1825000
1#
b1 C
1/
#1830000
b10101110 5
0/
#1835000
b0 H
b10 C
1/
#1840000
b10101111 5
0/
#1845000
bz "
bz :
0F
1%
0)
1(
b11 C
b0 G
1/
#1850000
0/
#1855000
b0 C
0(
1/
#1860000
b1000 J
b10110000 5
0/
#1865000
1/
#1870000
b1 H
13
b111011 0
b111011 8
b100001000 .
b100001000 7
0/
#1875000
b11 H
b111011 D
b100001000 &
b100001000 9
b100001000 B
1)
b1 G
1/
#1880000
b11 H
b10110010 5
03
0/
#1885000
b111011 "
b111011 :
1F
0#
0%
b11 G
1/
#1890000
b10110011 5
0/
#1895000
1#
b1 C
1/
#1900000
b10110100 5
0/
#1905000
b0 H
b10 C
1/
#1910000
b10110101 5
0/
#1915000
bz "
bz :
0F
1%
0)
1(
b11 C
b0 G
1/
#1920000
0/
#1925000
b0 C
0(
1/
#1930000
b1001 J
b10110110 5
0/
#1935000
1/
#1940000
b1 H
13
b1000010 0
b1000010 8
b100001001 .
b100001001 7
0/
#1945000
b11 H
b1000010 D
b100001001 &
b100001001 9
b100001001 B
1)
b1 G
1/
#1950000
b11 H
b10111000 5
03
0/
#1955000
b1000010 "
b1000010 :
1F
0#
0%
b11 G
1/
#1960000
b10111001 5
0/
#1965000
1#
b1 C
1/
#1970000
b10111010 5
0/
#1975000
b0 H
b10 C
1/
#1980000
b10111011 5
0/
#1985000
bz "
bz :
0F
1%
0)
1(
b11 C
b0 G
1/
#1990000
0/
#1995000
b0 C
0(
1/
#2000000
b1010 J
b10111100 5
0/
#2005000
1/
#2010000
b1 H
13
b1001001 0
b1001001 8
b100001010 .
b100001010 7
0/
